pandasai_huggingface/__init__.py
pandasai_huggingface/huggingface_text_gen.py
pandasai_huggingface-0.1.5.dist-info/METADATA
pandasai_huggingface-0.1.5.dist-info/WHEEL
pandasai_huggingface-0.1.5.dist-info/RECORD
